cuxrft/__init__.py
cuxrft/byte_converter.py
cuxrft/xarray.py
cuxrft/xr_controller_fft.py
cuxrft-0.0.17.dist-info/LICENSE
cuxrft-0.0.17.dist-info/METADATA
cuxrft-0.0.17.dist-info/WHEEL
cuxrft-0.0.17.dist-info/top_level.txt
cuxrft-0.0.17.dist-info/RECORD
