Metadata-Version: 2.1
Name: cuxrft
Version: 0.0.17
Summary: Performs FFTs on xarray by making use of cuda. Chunking and multiple GPUs in parallel supported.
Author-email: Tim Vogel <tim.vogel@physik.uni-kl.de>
Project-URL: Homepage, https://cuxrft.readthedocs.io/en/latest/
Project-URL: Repository, https://github.com/timvgl/CuXRFT.git
Project-URL: Issues, https://github.com/timvgl/CuXRFT/issues
Classifier: Programming Language :: Python :: 3
Classifier: License :: OSI Approved :: MIT License
Classifier: Operating System :: OS Independent
Requires-Python: >=3.8
License-File: LICENSE
